{"box_data": [{"position": {"minX": 416.75, "minY": 85.3125, "maxX": 670.0, "maxY": 309.25}, "class_id": 74, "box_caption": "pajeon 0.851", "scores": {"class_score": 0.85107421875}, "domain": "pixel"}, {"position": {"minX": 418.25, "minY": 85.9375, "maxX": 670.0, "maxY": 309.25}, "class_id": 34, "box_caption": "baechu-kimchi 0.009", "scores": {"class_score": 0.008544921875}, "domain": "pixel"}, {"position": {"minX": 417.75, "minY": 84.5625, "maxX": 666.0, "maxY": 308.0}, "class_id": 21, "box_caption": "dakgalbi 0.007", "scores": {"class_score": 0.006984710693359375}, "domain": "pixel"}, {"position": {"minX": 417.0, "minY": 85.4375, "maxX": 668.0, "maxY": 309.0}, "class_id": 19, "box_caption": "kkakdugi 0.007", "scores": {"class_score": 0.006961822509765625}, "domain": "pixel"}, {"position": {"minX": 418.25, "minY": 85.9375, "maxX": 670.0, "maxY": 309.25}, "class_id": 72, "box_caption": "combination-pizza 0.007", "scores": {"class_score": 0.006954193115234375}, "domain": "pixel"}, {"position": {"minX": 416.25, "minY": 84.375, "maxX": 668.0, "maxY": 307.5}, "class_id": 9, "box_caption": "gyeranhurai 0.005", "scores": {"class_score": 0.00513458251953125}, "domain": "pixel"}, {"position": {"minX": 418.25, "minY": 85.9375, "maxX": 670.0, "maxY": 309.25}, "class_id": 24, "box_caption": "dubu-gimchi 0.005", "scores": {"class_score": 0.004608154296875}, "domain": "pixel"}, {"position": {"minX": 418.25, "minY": 85.9375, "maxX": 670.0, "maxY": 309.25}, "class_id": 2, "box_caption": "galbi-jjim 0.004", "scores": {"class_score": 0.0041046142578125}, "domain": "pixel"}, {"position": {"minX": 415.5, "minY": 83.0625, "maxX": 670.5, "maxY": 311.0}, "class_id": 77, "box_caption": "haejangguk 0.004", "scores": {"class_score": 0.004085540771484375}, "domain": "pixel"}, {"position": {"minX": 415.5, "minY": 82.4375, "maxX": 671.5, "maxY": 310.0}, "class_id": 37, "box_caption": "bulgogi 0.004", "scores": {"class_score": 0.00394439697265625}, "domain": "pixel"}, {"position": {"minX": 417.0, "minY": 85.4375, "maxX": 668.0, "maxY": 309.0}, "class_id": 30, "box_caption": "margherita-pizza 0.004", "scores": {"class_score": 0.003726959228515625}, "domain": "pixel"}, {"position": {"minX": 417.0, "minY": 85.375, "maxX": 668.0, "maxY": 309.0}, "class_id": 70, "box_caption": "cheese-pizza 0.004", "scores": {"class_score": 0.00360870361328125}, "domain": "pixel"}, {"position": {"minX": 415.0, "minY": 85.1875, "maxX": 671.0, "maxY": 309.0}, "class_id": 1, "box_caption": "galbi-gui 0.003", "scores": {"class_score": 0.003459930419921875}, "domain": "pixel"}, {"position": {"minX": 416.25, "minY": 85.125, "maxX": 671.0, "maxY": 308.5}, "class_id": 16, "box_caption": "gimbap 0.003", "scores": {"class_score": 0.0033111572265625}, "domain": "pixel"}, {"position": {"minX": 415.0, "minY": 85.1875, "maxX": 671.0, "maxY": 309.0}, "class_id": 60, "box_caption": "jangeogui 0.003", "scores": {"class_score": 0.00308990478515625}, "domain": "pixel"}, {"position": {"minX": 415.5, "minY": 83.0625, "maxX": 670.5, "maxY": 311.0}, "class_id": 22, "box_caption": "dakjjim 0.003", "scores": {"class_score": 0.0029582977294921875}, "domain": "pixel"}, {"position": {"minX": 415.25, "minY": 84.8125, "maxX": 672.0, "maxY": 308.75}, "class_id": 71, "box_caption": "curry-rice 0.003", "scores": {"class_score": 0.0028057098388671875}, "domain": "pixel"}, {"position": {"minX": 417.5, "minY": 85.375, "maxX": 670.5, "maxY": 308.5}, "class_id": 8, "box_caption": "gyeran-mari 0.003", "scores": {"class_score": 0.002704620361328125}, "domain": "pixel"}, {"position": {"minX": 418.25, "minY": 85.9375, "maxX": 670.0, "maxY": 309.25}, "class_id": 0, "box_caption": "gaji-gui 0.003", "scores": {"class_score": 0.002643585205078125}, "domain": "pixel"}, {"position": {"minX": 417.5, "minY": 85.375, "maxX": 670.5, "maxY": 308.5}, "class_id": 36, "box_caption": "budae-jjigae 0.003", "scores": {"class_score": 0.00260162353515625}, "domain": "pixel"}, {"position": {"minX": 415.0, "minY": 85.1875, "maxX": 671.0, "maxY": 309.0}, "class_id": 65, "box_caption": "jjajangmyeon 0.002", "scores": {"class_score": 0.0024166107177734375}, "domain": "pixel"}, {"position": {"minX": 415.5, "minY": 82.4375, "maxX": 671.5, "maxY": 310.0}, "class_id": 13, "box_caption": "ojingeochae-muchim 0.002", "scores": {"class_score": 0.0023956298828125}, "domain": "pixel"}, {"position": {"minX": 415.5, "minY": 82.4375, "maxX": 671.5, "maxY": 310.0}, "class_id": 28, "box_caption": "ramyeon 0.002", "scores": {"class_score": 0.0023326873779296875}, "domain": "pixel"}, {"position": {"minX": 417.0, "minY": 85.375, "maxX": 668.0, "maxY": 309.0}, "class_id": 31, "box_caption": "mandu-guk 0.002", "scores": {"class_score": 0.0023136138916015625}, "domain": "pixel"}, {"position": {"minX": 415.5, "minY": 82.4375, "maxX": 671.5, "maxY": 310.0}, "class_id": 41, "box_caption": "samgyeopsal-gui 0.002", "scores": {"class_score": 0.002269744873046875}, "domain": "pixel"}, {"position": {"minX": 415.5, "minY": 82.4375, "maxX": 671.5, "maxY": 310.0}, "class_id": 45, "box_caption": "saengseonjeon 0.002", "scores": {"class_score": 0.0021915435791015625}, "domain": "pixel"}, {"position": {"minX": 415.5, "minY": 83.0625, "maxX": 670.5, "maxY": 311.0}, "class_id": 69, "box_caption": "jjinmandu 0.002", "scores": {"class_score": 0.00217437744140625}, "domain": "pixel"}, {"position": {"minX": 415.0, "minY": 85.1875, "maxX": 671.0, "maxY": 309.0}, "class_id": 29, "box_caption": "maneul-jangajji 0.002", "scores": {"class_score": 0.002166748046875}, "domain": "pixel"}, {"position": {"minX": 416.25, "minY": 85.125, "maxX": 671.0, "maxY": 308.5}, "class_id": 76, "box_caption": "haemuljjim 0.002", "scores": {"class_score": 0.0020923614501953125}, "domain": "pixel"}, {"position": {"minX": 417.0, "minY": 85.4375, "maxX": 668.0, "maxY": 309.0}, "class_id": 10, "box_caption": "godeungeo-gui 0.002", "scores": {"class_score": 0.002079010009765625}, "domain": "pixel"}, {"position": {"minX": 416.0, "minY": 84.1875, "maxX": 672.0, "maxY": 309.75}, "class_id": 12, "box_caption": "gochu-jangajji 0.002", "scores": {"class_score": 0.002063751220703125}, "domain": "pixel"}, {"position": {"minX": 415.5, "minY": 82.4375, "maxX": 671.5, "maxY": 310.0}, "class_id": 6, "box_caption": "gejang 0.002", "scores": {"class_score": 0.002002716064453125}, "domain": "pixel"}, {"position": {"minX": 415.5, "minY": 82.4375, "maxX": 671.5, "maxY": 310.0}, "class_id": 5, "box_caption": "geon-saewoo-bokkeum 0.002", "scores": {"class_score": 0.0019893646240234375}, "domain": "pixel"}, {"position": {"minX": 415.5, "minY": 82.4375, "maxX": 671.5, "maxY": 310.0}, "class_id": 50, "box_caption": "sigumchi-namul 0.002", "scores": {"class_score": 0.0019426345825195312}, "domain": "pixel"}, {"position": {"minX": 416.0, "minY": 84.1875, "maxX": 672.0, "maxY": 309.75}, "class_id": 32, "box_caption": "modeum-twigim 0.002", "scores": {"class_score": 0.001922607421875}, "domain": "pixel"}, {"position": {"minX": 418.25, "minY": 85.9375, "maxX": 670.0, "maxY": 309.25}, "class_id": 23, "box_caption": "doenjang-jjigae 0.002", "scores": {"class_score": 0.0018987655639648438}, "domain": "pixel"}, {"position": {"minX": 415.0, "minY": 83.5625, "maxX": 672.0, "maxY": 311.25}, "class_id": 81, "box_caption": "huin-juk 0.002", "scores": {"class_score": 0.0018787384033203125}, "domain": "pixel"}, {"position": {"minX": 417.75, "minY": 84.5625, "maxX": 666.0, "maxY": 308.0}, "class_id": 79, "box_caption": "huraideu-chicken 0.002", "scores": {"class_score": 0.0018138885498046875}, "domain": "pixel"}, {"position": {"minX": 415.5, "minY": 83.0625, "maxX": 670.5, "maxY": 311.0}, "class_id": 73, "box_caption": "kongguksu 0.002", "scores": {"class_score": 0.0017414093017578125}, "domain": "pixel"}, {"position": {"minX": 415.5, "minY": 83.0625, "maxX": 670.5, "maxY": 311.0}, "class_id": 54, "box_caption": "omeu-raiseu 0.002", "scores": {"class_score": 0.001728057861328125}, "domain": "pixel"}, {"position": {"minX": 415.5, "minY": 83.0625, "maxX": 670.5, "maxY": 311.0}, "class_id": 25, "box_caption": "tteokgalbi 0.002", "scores": {"class_score": 0.0017213821411132812}, "domain": "pixel"}, {"position": {"minX": 416.0, "minY": 84.1875, "maxX": 672.0, "maxY": 309.75}, "class_id": 52, "box_caption": "aehobak-bokkeum 0.002", "scores": {"class_score": 0.0017175674438476562}, "domain": "pixel"}, {"position": {"minX": 417.5, "minY": 85.375, "maxX": 670.5, "maxY": 308.5}, "class_id": 39, "box_caption": "bibim-naengmyeon 0.002", "scores": {"class_score": 0.001708984375}, "domain": "pixel"}, {"position": {"minX": 414.5, "minY": 83.875, "maxX": 672.5, "maxY": 309.5}, "class_id": 51, "box_caption": "al-bap 0.002", "scores": {"class_score": 0.001682281494140625}, "domain": "pixel"}, {"position": {"minX": 415.5, "minY": 84.0625, "maxX": 671.5, "maxY": 308.5}, "class_id": 33, "box_caption": "miyeokguk 0.002", "scores": {"class_score": 0.0016326904296875}, "domain": "pixel"}, {"position": {"minX": 415.5, "minY": 84.0625, "maxX": 671.5, "maxY": 308.5}, "class_id": 7, "box_caption": "gyeongdan 0.002", "scores": {"class_score": 0.0016012191772460938}, "domain": "pixel"}, {"position": {"minX": 418.25, "minY": 85.9375, "maxX": 670.0, "maxY": 309.25}, "class_id": 68, "box_caption": "jjukkumi-bokkeum 0.002", "scores": {"class_score": 0.0015993118286132812}, "domain": "pixel"}, {"position": {"minX": 415.5, "minY": 82.4375, "maxX": 671.5, "maxY": 310.0}, "class_id": 53, "box_caption": "yangnyeom-chicken 0.002", "scores": {"class_score": 0.0015974044799804688}, "domain": "pixel"}, {"position": {"minX": 415.0, "minY": 83.5625, "maxX": 672.0, "maxY": 311.25}, "class_id": 43, "box_caption": "saeu-bokkeumbap 0.002", "scores": {"class_score": 0.00159454345703125}, "domain": "pixel"}, {"position": {"minX": 415.5, "minY": 83.0625, "maxX": 670.5, "maxY": 311.0}, "class_id": 17, "box_caption": "kimchi-bokkeumbap 0.002", "scores": {"class_score": 0.0015850067138671875}, "domain": "pixel"}, {"position": {"minX": 416.25, "minY": 85.125, "maxX": 671.0, "maxY": 308.5}, "class_id": 56, "box_caption": "yubuchobap 0.002", "scores": {"class_score": 0.00157928466796875}, "domain": "pixel"}, {"position": {"minX": 415.5, "minY": 83.0625, "maxX": 670.5, "maxY": 311.0}, "class_id": 78, "box_caption": "hoe-muchim 0.002", "scores": {"class_score": 0.0015316009521484375}, "domain": "pixel"}, {"position": {"minX": 415.0, "minY": 83.5625, "maxX": 672.0, "maxY": 311.25}, "class_id": 49, "box_caption": "sundae 0.002", "scores": {"class_score": 0.0015163421630859375}, "domain": "pixel"}, {"position": {"minX": 415.5, "minY": 82.4375, "maxX": 671.5, "maxY": 310.0}, "class_id": 59, "box_caption": "japchae 0.001", "scores": {"class_score": 0.001438140869140625}, "domain": "pixel"}, {"position": {"minX": 415.0, "minY": 83.5625, "maxX": 672.0, "maxY": 311.25}, "class_id": 35, "box_caption": "bo-ssam 0.001", "scores": {"class_score": 0.0014295578002929688}, "domain": "pixel"}, {"position": {"minX": 415.5, "minY": 82.4375, "maxX": 671.5, "maxY": 310.0}, "class_id": 14, "box_caption": "gopchang-jeongol 0.001", "scores": {"class_score": 0.0013513565063476562}, "domain": "pixel"}, {"position": {"minX": 416.25, "minY": 85.125, "maxX": 671.0, "maxY": 308.5}, "class_id": 58, "box_caption": "japgokbap 0.001", "scores": {"class_score": 0.001346588134765625}, "domain": "pixel"}, {"position": {"minX": 417.0, "minY": 85.375, "maxX": 668.0, "maxY": 309.0}, "class_id": 18, "box_caption": "kimchi-jjigae 0.001", "scores": {"class_score": 0.0013456344604492188}, "domain": "pixel"}, {"position": {"minX": 415.0, "minY": 85.1875, "maxX": 671.0, "maxY": 309.0}, "class_id": 26, "box_caption": "tteokguk 0.001", "scores": {"class_score": 0.0013265609741210938}, "domain": "pixel"}, {"position": {"minX": 415.5, "minY": 84.625, "maxX": 673.5, "maxY": 310.0}, "class_id": 40, "box_caption": "bibimbap 0.001", "scores": {"class_score": 0.0013189315795898438}, "domain": "pixel"}, {"position": {"minX": 415.0, "minY": 83.5625, "maxX": 672.0, "maxY": 311.25}, "class_id": 62, "box_caption": "dwaejigogi-bokkeum 0.001", "scores": {"class_score": 0.0013170242309570312}, "domain": "pixel"}, {"position": {"minX": 415.0, "minY": 83.5625, "maxX": 672.0, "maxY": 311.25}, "class_id": 44, "box_caption": "saeu-twigim 0.001", "scores": {"class_score": 0.0013170242309570312}, "domain": "pixel"}, {"position": {"minX": 415.5, "minY": 83.0625, "maxX": 670.5, "maxY": 311.0}, "class_id": 42, "box_caption": "samgyetang 0.001", "scores": {"class_score": 0.00119781494140625}, "domain": "pixel"}, {"position": {"minX": 415.5, "minY": 83.0625, "maxX": 670.5, "maxY": 311.0}, "class_id": 63, "box_caption": "jokbal 0.001", "scores": {"class_score": 0.0011796951293945312}, "domain": "pixel"}, {"position": {"minX": 415.5, "minY": 83.0625, "maxX": 670.5, "maxY": 311.0}, "class_id": 66, "box_caption": "jjamppong 0.001", "scores": {"class_score": 0.0010728836059570312}, "domain": "pixel"}, {"position": {"minX": 415.5, "minY": 83.0625, "maxX": 670.5, "maxY": 311.0}, "class_id": 55, "box_caption": "udong 0.001", "scores": {"class_score": 0.0010652542114257812}, "domain": "pixel"}, {"position": {"minX": 415.5, "minY": 83.0625, "maxX": 670.5, "maxY": 311.0}, "class_id": 57, "box_caption": "yukhoe 0.001", "scores": {"class_score": 0.001056671142578125}, "domain": "pixel"}, {"position": {"minX": 415.0, "minY": 84.8125, "maxX": 673.0, "maxY": 308.75}, "class_id": 48, "box_caption": "sukjunamul 0.001", "scores": {"class_score": 0.0010213851928710938}, "domain": "pixel"}], "class_labels": {"0": "gaji-gui", "1": "galbi-gui", "2": "galbi-jjim", "3": "gamja-bokkeum", "4": "gamja-twigim", "5": "geon-saewoo-bokkeum", "6": "gejang", "7": "gyeongdan", "8": "gyeran-mari", "9": "gyeranhurai", "10": "godeungeo-gui", "11": "gorgonzola-pizza", "12": "gochu-jangajji", "13": "ojingeochae-muchim", "14": "gopchang-jeongol", "15": "gunmandu", "16": "gimbap", "17": "kimchi-bokkeumbap", "18": "kimchi-jjigae", "19": "kkakdugi", "20": "naengmyeon", "21": "dakgalbi", "22": "dakjjim", "23": "doenjang-jjigae", "24": "dubu-gimchi", "25": "tteokgalbi", "26": "tteokguk", "27": "tteokbokki", "28": "ramyeon", "29": "maneul-jangajji", "30": "margherita-pizza", "31": "mandu-guk", "32": "modeum-twigim", "33": "miyeokguk", "34": "baechu-kimchi", "35": "bo-ssam", "36": "budae-jjigae", "37": "bulgogi", "38": "bibim-guksu", "39": "bibim-naengmyeon", "40": "bibimbap", "41": "samgyeopsal-gui", "42": "samgyetang", "43": "saeu-bokkeumbap", "44": "saeu-twigim", "45": "saengseonjeon", "46": "soseji-bokkeum", "47": "songpyeon", "48": "sukjunamul", "49": "sundae", "50": "sigumchi-namul", "51": "al-bap", "52": "aehobak-bokkeum", "53": "yangnyeom-chicken", "54": "omeu-raiseu", "55": "udong", "56": "yubuchobap", "57": "yukhoe", "58": "japgokbap", "59": "japchae", "60": "jangeogui", "61": "jangjorim", "62": "dwaejigogi-bokkeum", "63": "jokbal", "64": "gimgaru-jumeokbap", "65": "jjajangmyeon", "66": "jjamppong", "67": "jjokgalbigui", "68": "jjukkumi-bokkeum", "69": "jjinmandu", "70": "cheese-pizza", "71": "curry-rice", "72": "combination-pizza", "73": "kongguksu", "74": "pajeon", "75": "hangwa", "76": "haemuljjim", "77": "haejangguk", "78": "hoe-muchim", "79": "huraideu-chicken", "80": "hunjeori", "81": "huin-juk"}}